gcrc/__main__.py
gcrc/gcloud.py
gcrc/main.py
gcrc/settings.py
gcrc/utils.py
gcrc-1.0.6.dist-info/entry_points.txt
gcrc-1.0.6.dist-info/LICENSE.md
gcrc-1.0.6.dist-info/WHEEL
gcrc-1.0.6.dist-info/METADATA
gcrc-1.0.6.dist-info/RECORD
