Metadata-Version: 2.1
Name: gcrc
Version: 1.0.6
Summary: Google Container Registry Cleanup utility
Home-page: https://github.com/lietu/gcrc
License: BSD-3-Clause
Author: Janne Enberg
Author-email: janne.enberg@lietu.net
Requires-Python: >=3.9,<4.0
Classifier: License :: OSI Approved :: BSD License
Classifier: Programming Language :: Python :: 3
Classifier: Programming Language :: Python :: 3.9
Requires-Dist: colorama (>=0.4.4,<0.5.0)
Requires-Dist: pydantic[dotenv] (>=1.8.2,<2.0.0)
Requires-Dist: python-dateutil (>=2.8.2,<3.0.0)
Requires-Dist: requests (>=2.26.0,<3.0.0)
Requires-Dist: typer[colorama] (>=0.3.2,<0.4.0)
Project-URL: Repository, https://github.com/lietu/gcrc
